google/cloud/scheduler/__init__.py
google/cloud/scheduler/gapic_version.py
google/cloud/scheduler/py.typed
google/cloud/scheduler_v1/__init__.py
google/cloud/scheduler_v1/gapic_metadata.json
google/cloud/scheduler_v1/gapic_version.py
google/cloud/scheduler_v1/py.typed
google/cloud/scheduler_v1/services/__init__.py
google/cloud/scheduler_v1/services/cloud_scheduler/__init__.py
google/cloud/scheduler_v1/services/cloud_scheduler/async_client.py
google/cloud/scheduler_v1/services/cloud_scheduler/client.py
google/cloud/scheduler_v1/services/cloud_scheduler/pagers.py
google/cloud/scheduler_v1/services/cloud_scheduler/transports/__init__.py
google/cloud/scheduler_v1/services/cloud_scheduler/transports/base.py
google/cloud/scheduler_v1/services/cloud_scheduler/transports/grpc.py
google/cloud/scheduler_v1/services/cloud_scheduler/transports/grpc_asyncio.py
google/cloud/scheduler_v1/services/cloud_scheduler/transports/rest.py
google/cloud/scheduler_v1/services/cloud_scheduler/transports/rest_base.py
google/cloud/scheduler_v1/types/__init__.py
google/cloud/scheduler_v1/types/cloudscheduler.py
google/cloud/scheduler_v1/types/job.py
google/cloud/scheduler_v1/types/target.py
google/cloud/scheduler_v1beta1/__init__.py
google/cloud/scheduler_v1beta1/gapic_metadata.json
google/cloud/scheduler_v1beta1/gapic_version.py
google/cloud/scheduler_v1beta1/py.typed
google/cloud/scheduler_v1beta1/services/__init__.py
google/cloud/scheduler_v1beta1/services/cloud_scheduler/__init__.py
google/cloud/scheduler_v1beta1/services/cloud_scheduler/async_client.py
google/cloud/scheduler_v1beta1/services/cloud_scheduler/client.py
google/cloud/scheduler_v1beta1/services/cloud_scheduler/pagers.py
google/cloud/scheduler_v1beta1/services/cloud_scheduler/transports/__init__.py
google/cloud/scheduler_v1beta1/services/cloud_scheduler/transports/base.py
google/cloud/scheduler_v1beta1/services/cloud_scheduler/transports/grpc.py
google/cloud/scheduler_v1beta1/services/cloud_scheduler/transports/grpc_asyncio.py
google_cloud_scheduler-2.17.0.dist-info/licenses/LICENSE
google_cloud_scheduler-2.17.0.dist-info/METADATA
google_cloud_scheduler-2.17.0.dist-info/WHEEL
google_cloud_scheduler-2.17.0.dist-info/top_level.txt
google_cloud_scheduler-2.17.0.dist-info/RECORD
